pgtoolbox/__init__.py
pgtoolbox/db_toolbox.py
pgtoolbox-0.0.10.dist-info/LICENSE
pgtoolbox-0.0.10.dist-info/METADATA
pgtoolbox-0.0.10.dist-info/WHEEL
pgtoolbox-0.0.10.dist-info/top_level.txt
pgtoolbox-0.0.10.dist-info/RECORD
