Metadata-Version: 2.1
Name: pgtoolbox
Version: 0.0.10
Summary: A python-postgres database toolbox
Home-page: UNKNOWN
Author: Bernard Louis Alecu
Author-email: bernard.alecu10@gmail.com
License: UNKNOWN
Platform: UNKNOWN
Classifier: Programming Language :: Python :: 3
Classifier: License :: OSI Approved :: MIT License
Classifier: Operating System :: OS Independent
Requires-Python: >=3.6
Requires-Dist: pg8000 (>=1.13.2)
